promb/__init__.py
promb/__version__.py
promb/cli.py
promb/db.py
promb/formatting.py
promb/netmhc.py
promb/parsing.py
promb/resources/OASis_9mers_v1_10perc_subjects.txt.gz
promb/resources/uniprot_sprot_human.fasta.gz
promb/resources/uniprotkb_proteome_UP000005640_2025_04_21.fasta.gz
promb-1.0.2.dist-info/licenses/LICENSE
promb-1.0.2.dist-info/licenses/LICENSES_THIRD_PARTY
promb-1.0.2.dist-info/METADATA
promb-1.0.2.dist-info/WHEEL
promb-1.0.2.dist-info/entry_points.txt
promb-1.0.2.dist-info/top_level.txt
promb-1.0.2.dist-info/RECORD
