Metadata-Version: 2.4
Name: promb
Version: 1.0.2
Summary: promb: protein mutation burden
Home-page: https://github.com/MSDLLCPapers/promb
Author: David Prihoda
Author-email: david.prihoda@gmail.com
License: MIT
Keywords: antibody humanness,de-novo humanness,human peptide content,oasis,biophi,mutation burden,promb
Classifier: Programming Language :: Python :: 3
Requires-Python: >=3.8
License-File: LICENSE
License-File: LICENSES_THIRD_PARTY
Requires-Dist: scipy
Requires-Dist: pandas
Requires-Dist: tqdm
Dynamic: author
Dynamic: author-email
Dynamic: classifier
Dynamic: description
Dynamic: description-content-type
Dynamic: home-page
Dynamic: keywords
Dynamic: license
Dynamic: license-file
Dynamic: requires-dist
Dynamic: requires-python
Dynamic: summary
